cmlibs/__init__.py
cmlibs/argon/__init__.py
cmlibs/argon/argondocument.py
cmlibs/argon/argonerror.py
cmlibs/argon/argonlogger.py
cmlibs/argon/argonmaterials.py
cmlibs/argon/argonmodelsources.py
cmlibs/argon/argonregion.py
cmlibs/argon/argonsceneviewer.py
cmlibs/argon/argonspectrums.py
cmlibs/argon/argontessellations.py
cmlibs/argon/argonviews.py
cmlibs/argon/utilities.py
cmlibs/argon/settings/__init__.py
cmlibs/argon/settings/mainsettings.py
cmlibs.argon-0.4.3.dist-info/LICENSE
cmlibs.argon-0.4.3.dist-info/METADATA
cmlibs.argon-0.4.3.dist-info/WHEEL
cmlibs.argon-0.4.3.dist-info/top_level.txt
cmlibs.argon-0.4.3.dist-info/RECORD
