Metadata-Version: 2.1
Name: cmlibs.argon
Version: 0.4.3
Summary: CMLibs Argon visualisation descriptions.
Home-page: https://github.com/cmlibs-python/cmlibs.argon
Author: Hugh Sorby
Author-email: h.sorby@auckland.ac.nz
License: Apache Software License
License-File: LICENSE
Requires-Dist: cmlibs.zinc
Requires-Dist: packaging
